{
  "updated_at": "2026-06-29T17:42:11.271512+03:00",
  "fallback_aktif": false,
  "fallback_aciklama": null,
  "agirlik_metodoloji": {
    "kaynak": "BİST CSV + İş Yatırım (halka açıklık × piyasa değeri, %10 cap)",
    "son_basarili_cekim": "2026-06-29T13:58:22.399757+03:00",
    "fallback_aktif": false,
    "fallback_aciklama": null
  },
  "endeks_degisim": {
    "daily": null,
    "weekly": null,
    "monthly": null
  },
  "endeks_katki_toplam": {
    "daily": -0.9267,
    "weekly": -3.7501,
    "monthly": 6.7466
  },
  "dogrulama_farki_bps": {
    "daily": null,
    "weekly": null,
    "monthly": null
  },
  "hisse_sayisi": 100,
  "stocks": {
    "daily": [
      {
        "ticker": "RALYH",
        "name": "Ral Yatırım Holding",
        "agirlik": 0.4218,
        "degisim": 9.9747,
        "katki": 0.0421
      },
      {
        "ticker": "CCOLA",
        "name": "Coca-Cola İçecek A.Ş",
        "agirlik": 1.5229,
        "degisim": 2.3385,
        "katki": 0.0356
      },
      {
        "ticker": "ENJSA",
        "name": "Enerjisa Enerji",
        "agirlik": 0.5527,
        "degisim": 3.3106,
        "katki": 0.0183
      },
      {
        "ticker": "BRSAN",
        "name": "Borusan Birleşik Boru Fab.",
        "agirlik": 0.3866,
        "degisim": 4.5956,
        "katki": 0.0178
      },
      {
        "ticker": "KTLEV",
        "name": "Katılımevim",
        "agirlik": 2.044,
        "degisim": 0.8173,
        "katki": 0.0167
      },
      {
        "ticker": "MPARK",
        "name": "MLP Sağlık Hizmetleri",
        "agirlik": 0.7731,
        "degisim": 1.8779,
        "katki": 0.0145
      },
      {
        "ticker": "PATEK",
        "name": "Pasifik Teknoloji",
        "agirlik": 0.146,
        "degisim": 9.9634,
        "katki": 0.0145
      },
      {
        "ticker": "EUPWR",
        "name": "Europower Enerji",
        "agirlik": 0.4492,
        "degisim": 2.6215,
        "katki": 0.0118
      },
      {
        "ticker": "GESAN",
        "name": "Girişim Elektrik",
        "agirlik": 0.2749,
        "degisim": 3.5688,
        "katki": 0.0098
      },
      {
        "ticker": "VESTL",
        "name": "Vestel Elektronik",
        "agirlik": 0.0939,
        "degisim": 9.9846,
        "katki": 0.0094
      },
      {
        "ticker": "BSOKE",
        "name": "Batıçim Çimento",
        "agirlik": 0.3342,
        "degisim": 2.7042,
        "katki": 0.009
      },
      {
        "ticker": "AKSEN",
        "name": "Aksa Enerji",
        "agirlik": 0.4477,
        "degisim": 1.9976,
        "katki": 0.0089
      },
      {
        "ticker": "ALTNY",
        "name": "Altınay Savunma",
        "agirlik": 0.1331,
        "degisim": 5.4638,
        "katki": 0.0073
      },
      {
        "ticker": "SKBNK",
        "name": "Şekerbank",
        "agirlik": 0.4383,
        "degisim": 1.6181,
        "katki": 0.0071
      },
      {
        "ticker": "AGHOL",
        "name": "Anadolu Grubu Holding",
        "agirlik": 0.6696,
        "degisim": 1.0284,
        "katki": 0.0069
      },
      {
        "ticker": "ALARK",
        "name": "Alarko Holding",
        "agirlik": 0.3428,
        "degisim": 1.9962,
        "katki": 0.0068
      },
      {
        "ticker": "OTKAR",
        "name": "Otokar",
        "agirlik": 0.2724,
        "degisim": 2.3208,
        "katki": 0.0063
      },
      {
        "ticker": "KLRHO",
        "name": "Kiler Holding",
        "agirlik": 0.311,
        "degisim": 1.9026,
        "katki": 0.0059
      },
      {
        "ticker": "ZOREN",
        "name": "Zorlu Enerji",
        "agirlik": 0.1211,
        "degisim": 4.5614,
        "katki": 0.0055
      },
      {
        "ticker": "MIATK",
        "name": "Mia Teknoloji",
        "agirlik": 0.2647,
        "degisim": 1.9667,
        "katki": 0.0052
      },
      {
        "ticker": "CVKMD",
        "name": "Cvk Maden",
        "agirlik": 0.3824,
        "degisim": 1.2513,
        "katki": 0.0048
      },
      {
        "ticker": "SOKM",
        "name": "Şok Marketler",
        "agirlik": 0.265,
        "degisim": 1.7101,
        "katki": 0.0045
      },
      {
        "ticker": "AKSA",
        "name": "Aksa",
        "agirlik": 0.3181,
        "degisim": 1.3758,
        "katki": 0.0044
      },
      {
        "ticker": "ODAS",
        "name": "Odaş Elektrik Üretim",
        "agirlik": 0.2082,
        "degisim": 2.0238,
        "katki": 0.0042
      },
      {
        "ticker": "ENKAI",
        "name": "Enka İnşaat",
        "agirlik": 1.0308,
        "degisim": 0.3852,
        "katki": 0.004
      },
      {
        "ticker": "TABGD",
        "name": "Tab Gıda",
        "agirlik": 0.3215,
        "degisim": 1.1602,
        "katki": 0.0037
      },
      {
        "ticker": "AEFES",
        "name": "Anadolu Efes",
        "agirlik": 0.935,
        "degisim": 0.3763,
        "katki": 0.0035
      },
      {
        "ticker": "TKFEN",
        "name": "Tekfen Holding",
        "agirlik": 0.2556,
        "degisim": 0.7763,
        "katki": 0.002
      },
      {
        "ticker": "BRYAT",
        "name": "Borusan Yatırım",
        "agirlik": 0.1844,
        "degisim": 1.0701,
        "katki": 0.002
      },
      {
        "ticker": "PAHOL",
        "name": "Pasifik Holding",
        "agirlik": 0.1367,
        "degisim": 1.3333,
        "katki": 0.0018
      },
      {
        "ticker": "TTKOM",
        "name": "Türk Telekom",
        "agirlik": 0.6553,
        "degisim": 0.241,
        "katki": 0.0016
      },
      {
        "ticker": "GLRMK",
        "name": "Gülermak Ağır Sanayi",
        "agirlik": 0.3338,
        "degisim": 0.1744,
        "katki": 0.0006
      },
      {
        "ticker": "EUREN",
        "name": "Europen Endüstri",
        "agirlik": 0.1059,
        "degisim": 0.2237,
        "katki": 0.0002
      },
      {
        "ticker": "SAHOL",
        "name": "Sabancı Holding",
        "agirlik": 2.4297,
        "degisim": 0.0,
        "katki": 0.0
      },
      {
        "ticker": "ISMEN",
        "name": "İş Yatırım",
        "agirlik": 0.3653,
        "degisim": 0.0,
        "katki": 0.0
      },
      {
        "ticker": "GSRAY",
        "name": "Galatasaray Sportif A.Ş",
        "agirlik": 0.1255,
        "degisim": 0.0,
        "katki": 0.0
      },
      {
        "ticker": "GRTHO",
        "name": "GrainTurk Tarım",
        "agirlik": 0.1433,
        "degisim": -0.0815,
        "katki": -0.0001
      },
      {
        "ticker": "OYAKC",
        "name": "Oyak Çimento",
        "agirlik": 0.4566,
        "degisim": -0.0961,
        "katki": -0.0004
      },
      {
        "ticker": "BERA",
        "name": "Bera Holding",
        "agirlik": 0.171,
        "degisim": -0.4938,
        "katki": -0.0008
      },
      {
        "ticker": "REEDR",
        "name": "Reeder",
        "agirlik": 0.0898,
        "degisim": -1.0526,
        "katki": -0.0009
      },
      {
        "ticker": "CWENE",
        "name": "Cw Enerji",
        "agirlik": 0.2405,
        "degisim": -0.4348,
        "katki": -0.001
      },
      {
        "ticker": "FENER",
        "name": "Fenerbahce Futbol A.Ş.",
        "agirlik": 0.1628,
        "degisim": -0.6579,
        "katki": -0.0011
      },
      {
        "ticker": "GRSEL",
        "name": "Gürsel Taşımacılık",
        "agirlik": 0.1577,
        "degisim": -0.7329,
        "katki": -0.0012
      },
      {
        "ticker": "TUKAS",
        "name": "Tukaş",
        "agirlik": 0.1332,
        "degisim": -0.8696,
        "katki": -0.0012
      },
      {
        "ticker": "IZENR",
        "name": "İzdemir Enerji",
        "agirlik": 0.1769,
        "degisim": -0.7905,
        "katki": -0.0014
      },
      {
        "ticker": "TUREX",
        "name": "Tureks Tur.Taşımacılık",
        "agirlik": 0.0737,
        "degisim": -1.8642,
        "katki": -0.0014
      },
      {
        "ticker": "BTCIM",
        "name": "Batıçim",
        "agirlik": 0.4921,
        "degisim": -0.3322,
        "katki": -0.0016
      },
      {
        "ticker": "DOHOL",
        "name": "Doğan Holding",
        "agirlik": 0.45,
        "degisim": -0.3784,
        "katki": -0.0017
      },
      {
        "ticker": "ENERY",
        "name": "Enerya Enerji",
        "agirlik": 0.4022,
        "degisim": -0.5149,
        "katki": -0.0021
      },
      {
        "ticker": "ULKER",
        "name": "Ülker Bisküvi",
        "agirlik": 0.3834,
        "degisim": -0.5859,
        "katki": -0.0022
      },
      {
        "ticker": "ECILC",
        "name": "Eczacıbaşı İlaç",
        "agirlik": 0.2621,
        "degisim": -0.8519,
        "katki": -0.0022
      },
      {
        "ticker": "GENIL",
        "name": "Gen İlaç",
        "agirlik": 0.237,
        "degisim": -0.9657,
        "katki": -0.0023
      },
      {
        "ticker": "DOAS",
        "name": "Doğuş Otomotiv",
        "agirlik": 0.3641,
        "degisim": -0.6525,
        "katki": -0.0024
      },
      {
        "ticker": "BALSU",
        "name": "Balsu Gıda",
        "agirlik": 0.1178,
        "degisim": -2.3131,
        "katki": -0.0027
      },
      {
        "ticker": "TRENJ",
        "name": "TR Doğal Enerji Kaynakları",
        "agirlik": 0.1695,
        "degisim": -2.0528,
        "katki": -0.0035
      },
      {
        "ticker": "KRDMD",
        "name": "Kardemir (D)",
        "agirlik": 0.6706,
        "degisim": -0.5424,
        "katki": -0.0036
      },
      {
        "ticker": "DAPGM",
        "name": "Dap Gayrimenkul",
        "agirlik": 0.2083,
        "degisim": -1.7476,
        "katki": -0.0036
      },
      {
        "ticker": "OBAMS",
        "name": "Oba Makarnacılık",
        "agirlik": 0.1105,
        "degisim": -3.4056,
        "katki": -0.0038
      },
      {
        "ticker": "TSKB",
        "name": "TSKB",
        "agirlik": 0.3209,
        "degisim": -1.2285,
        "katki": -0.0039
      },
      {
        "ticker": "QUAGR",
        "name": "QUA Granite",
        "agirlik": 0.1125,
        "degisim": -3.5265,
        "katki": -0.004
      },
      {
        "ticker": "TUPRS",
        "name": "Tüpraş",
        "agirlik": 4.6768,
        "degisim": -0.0912,
        "katki": -0.0043
      },
      {
        "ticker": "CANTE",
        "name": "Çan2 Termik A.S",
        "agirlik": 0.2252,
        "degisim": -2.1429,
        "katki": -0.0048
      },
      {
        "ticker": "ARCLK",
        "name": "Arçelik",
        "agirlik": 0.2773,
        "degisim": -2.1133,
        "katki": -0.0059
      },
      {
        "ticker": "PSGYO",
        "name": "Pasifik GYO",
        "agirlik": 0.2268,
        "degisim": -2.8011,
        "katki": -0.0064
      },
      {
        "ticker": "ANSGR",
        "name": "Anadolu Sigorta",
        "agirlik": 0.444,
        "degisim": -1.4957,
        "katki": -0.0066
      },
      {
        "ticker": "EKGYO",
        "name": "Emlak Konut GYO",
        "agirlik": 0.8765,
        "degisim": -0.7634,
        "katki": -0.0067
      },
      {
        "ticker": "VAKBN",
        "name": "Vakıfbank",
        "agirlik": 0.551,
        "degisim": -1.2743,
        "katki": -0.007
      },
      {
        "ticker": "KUYAS",
        "name": "Kuyas Yatırım AŞ",
        "agirlik": 0.6179,
        "degisim": -1.25,
        "katki": -0.0077
      },
      {
        "ticker": "HALKB",
        "name": "Halkbank",
        "agirlik": 0.6056,
        "degisim": -1.4078,
        "katki": -0.0085
      },
      {
        "ticker": "SARKY",
        "name": "Sarkuysan",
        "agirlik": 0.5231,
        "degisim": -1.6272,
        "katki": -0.0085
      },
      {
        "ticker": "SISE",
        "name": "Şişecam",
        "agirlik": 1.4961,
        "degisim": -0.5737,
        "katki": -0.0086
      },
      {
        "ticker": "FROTO",
        "name": "Ford Otosan",
        "agirlik": 1.2206,
        "degisim": -0.7536,
        "katki": -0.0092
      },
      {
        "ticker": "PETKM",
        "name": "Petkim",
        "agirlik": 0.5427,
        "degisim": -1.8897,
        "katki": -0.0103
      },
      {
        "ticker": "MAVI",
        "name": "Mavi Giyim Sanayi Tic.A.S",
        "agirlik": 0.5241,
        "degisim": -2.1565,
        "katki": -0.0113
      },
      {
        "ticker": "CIMSA",
        "name": "Çimsa",
        "agirlik": 0.4765,
        "degisim": -2.4878,
        "katki": -0.0119
      },
      {
        "ticker": "HEKTS",
        "name": "Hektaş",
        "agirlik": 0.2888,
        "degisim": -4.3988,
        "katki": -0.0127
      },
      {
        "ticker": "MAGEN",
        "name": "Margün Enerji",
        "agirlik": 0.27,
        "degisim": -5.3704,
        "katki": -0.0145
      },
      {
        "ticker": "PGSUS",
        "name": "Pegasus Hava Taşımacılığı",
        "agirlik": 0.95,
        "degisim": -1.6102,
        "katki": -0.0153
      },
      {
        "ticker": "TURSG",
        "name": "Türkiye Sigorta",
        "agirlik": 0.666,
        "degisim": -2.5397,
        "katki": -0.0169
      },
      {
        "ticker": "TCELL",
        "name": "Turkcell",
        "agirlik": 2.3792,
        "degisim": -0.7214,
        "katki": -0.0172
      },
      {
        "ticker": "GARAN",
        "name": "Garanti Bankası",
        "agirlik": 1.8542,
        "degisim": -0.9393,
        "katki": -0.0174
      },
      {
        "ticker": "TAVHL",
        "name": "TAV Holding",
        "agirlik": 1.1704,
        "degisim": -1.5817,
        "katki": -0.0185
      },
      {
        "ticker": "TRMET",
        "name": "TR Anadolu Metal",
        "agirlik": 0.4086,
        "degisim": -4.647,
        "katki": -0.019
      },
      {
        "ticker": "ISCTR",
        "name": "İş Bankası (C)",
        "agirlik": 2.7119,
        "degisim": -0.8141,
        "katki": -0.0221
      },
      {
        "ticker": "AKBNK",
        "name": "Akbank",
        "agirlik": 4.8691,
        "degisim": -0.5178,
        "katki": -0.0252
      },
      {
        "ticker": "EFOR",
        "name": "Efor Yat. San.",
        "agirlik": 0.2539,
        "degisim": -10.0,
        "katki": -0.0254
      },
      {
        "ticker": "TRALT",
        "name": "Türk Altın",
        "agirlik": 1.0143,
        "degisim": -2.9813,
        "katki": -0.0302
      },
      {
        "ticker": "MGROS",
        "name": "Migros",
        "agirlik": 1.4428,
        "degisim": -2.1786,
        "katki": -0.0314
      },
      {
        "ticker": "TOASO",
        "name": "Tofaş Fabrika",
        "agirlik": 0.8923,
        "degisim": -3.5385,
        "katki": -0.0316
      },
      {
        "ticker": "SASA",
        "name": "Sasa Polyester Sanayi A.Ş.",
        "agirlik": 1.3667,
        "degisim": -2.381,
        "katki": -0.0325
      },
      {
        "ticker": "GUBRF",
        "name": "Gübre Fabrikaları",
        "agirlik": 0.7703,
        "degisim": -5.4716,
        "katki": -0.0421
      },
      {
        "ticker": "KCHOL",
        "name": "Koç Holding",
        "agirlik": 3.0118,
        "degisim": -1.4127,
        "katki": -0.0425
      },
      {
        "ticker": "THYAO",
        "name": "Türk Hava Yolları",
        "agirlik": 5.2206,
        "degisim": -0.8314,
        "katki": -0.0434
      },
      {
        "ticker": "YKBNK",
        "name": "Yapı Kredi Bankası",
        "agirlik": 3.0128,
        "degisim": -1.574,
        "katki": -0.0474
      },
      {
        "ticker": "PASEU",
        "name": "Pasifik Eurasia",
        "agirlik": 0.6325,
        "degisim": -9.9608,
        "katki": -0.063
      },
      {
        "ticker": "BIMAS",
        "name": "Bim Birleşik Mağazalar A.Ş",
        "agirlik": 7.0447,
        "degisim": -1.0013,
        "katki": -0.0705
      },
      {
        "ticker": "EREGL",
        "name": "Ereğli Demir Çelik",
        "agirlik": 3.1372,
        "degisim": -2.3742,
        "katki": -0.0745
      },
      {
        "ticker": "ASTOR",
        "name": "Astor Enerji",
        "agirlik": 2.8133,
        "degisim": -3.1924,
        "katki": -0.0898
      },
      {
        "ticker": "DSTKF",
        "name": "Destek Finans Faktoring",
        "agirlik": 6.6843,
        "degisim": -1.5873,
        "katki": -0.1061
      },
      {
        "ticker": "ASELS",
        "name": "Aselsan",
        "agirlik": 9.6902,
        "degisim": -1.5214,
        "katki": -0.1474
      }
    ],
    "weekly": [
      {
        "ticker": "DSTKF",
        "name": "Destek Finans Faktoring",
        "agirlik": 6.6843,
        "degisim": 3.3333,
        "katki": 0.2228
      },
      {
        "ticker": "CCOLA",
        "name": "Coca-Cola İçecek A.Ş",
        "agirlik": 1.5229,
        "degisim": 7.7771,
        "katki": 0.1184
      },
      {
        "ticker": "EREGL",
        "name": "Ereğli Demir Çelik",
        "agirlik": 3.1372,
        "degisim": 1.9336,
        "katki": 0.0607
      },
      {
        "ticker": "THYAO",
        "name": "Türk Hava Yolları",
        "agirlik": 5.2206,
        "degisim": 1.0008,
        "katki": 0.0522
      },
      {
        "ticker": "TKFEN",
        "name": "Tekfen Holding",
        "agirlik": 0.2556,
        "degisim": 8.5932,
        "katki": 0.022
      },
      {
        "ticker": "BALSU",
        "name": "Balsu Gıda",
        "agirlik": 0.1178,
        "degisim": 17.6166,
        "katki": 0.0208
      },
      {
        "ticker": "ALARK",
        "name": "Alarko Holding",
        "agirlik": 0.3428,
        "degisim": 4.9902,
        "katki": 0.0171
      },
      {
        "ticker": "OTKAR",
        "name": "Otokar",
        "agirlik": 0.2724,
        "degisim": 4.8985,
        "katki": 0.0133
      },
      {
        "ticker": "VESTL",
        "name": "Vestel Elektronik",
        "agirlik": 0.0939,
        "degisim": 13.4707,
        "katki": 0.0126
      },
      {
        "ticker": "AEFES",
        "name": "Anadolu Efes",
        "agirlik": 0.935,
        "degisim": 1.3295,
        "katki": 0.0124
      },
      {
        "ticker": "PATEK",
        "name": "Pasifik Teknoloji",
        "agirlik": 0.146,
        "degisim": 5.1573,
        "katki": 0.0075
      },
      {
        "ticker": "BSOKE",
        "name": "Batıçim Çimento",
        "agirlik": 0.3342,
        "degisim": 2.0285,
        "katki": 0.0068
      },
      {
        "ticker": "ALTNY",
        "name": "Altınay Savunma",
        "agirlik": 0.1331,
        "degisim": 4.2714,
        "katki": 0.0057
      },
      {
        "ticker": "ZOREN",
        "name": "Zorlu Enerji",
        "agirlik": 0.1211,
        "degisim": 1.7065,
        "katki": 0.0021
      },
      {
        "ticker": "KLRHO",
        "name": "Kiler Holding",
        "agirlik": 0.311,
        "degisim": 0.5522,
        "katki": 0.0017
      },
      {
        "ticker": "AGHOL",
        "name": "Anadolu Grubu Holding",
        "agirlik": 0.6696,
        "degisim": 0.1199,
        "katki": 0.0008
      },
      {
        "ticker": "IZENR",
        "name": "İzdemir Enerji",
        "agirlik": 0.1769,
        "degisim": 0.4,
        "katki": 0.0007
      },
      {
        "ticker": "GRSEL",
        "name": "Gürsel Taşımacılık",
        "agirlik": 0.1577,
        "degisim": -0.082,
        "katki": -0.0001
      },
      {
        "ticker": "PAHOL",
        "name": "Pasifik Holding",
        "agirlik": 0.1367,
        "degisim": -0.6536,
        "katki": -0.0009
      },
      {
        "ticker": "ARCLK",
        "name": "Arçelik",
        "agirlik": 0.2773,
        "degisim": -1.1639,
        "katki": -0.0032
      },
      {
        "ticker": "GENIL",
        "name": "Gen İlaç",
        "agirlik": 0.237,
        "degisim": -1.4941,
        "katki": -0.0035
      },
      {
        "ticker": "GSRAY",
        "name": "Galatasaray Sportif A.Ş",
        "agirlik": 0.1255,
        "degisim": -2.8571,
        "katki": -0.0036
      },
      {
        "ticker": "SOKM",
        "name": "Şok Marketler",
        "agirlik": 0.265,
        "degisim": -1.409,
        "katki": -0.0037
      },
      {
        "ticker": "EUREN",
        "name": "Europen Endüstri",
        "agirlik": 0.1059,
        "degisim": -4.0685,
        "katki": -0.0043
      },
      {
        "ticker": "DOHOL",
        "name": "Doğan Holding",
        "agirlik": 0.45,
        "degisim": -1.0338,
        "katki": -0.0047
      },
      {
        "ticker": "ISMEN",
        "name": "İş Yatırım",
        "agirlik": 0.3653,
        "degisim": -1.2945,
        "katki": -0.0047
      },
      {
        "ticker": "TUKAS",
        "name": "Tukaş",
        "agirlik": 0.1332,
        "degisim": -4.2017,
        "katki": -0.0056
      },
      {
        "ticker": "REEDR",
        "name": "Reeder",
        "agirlik": 0.0898,
        "degisim": -6.2678,
        "katki": -0.0056
      },
      {
        "ticker": "QUAGR",
        "name": "QUA Granite",
        "agirlik": 0.1125,
        "degisim": -5.198,
        "katki": -0.0058
      },
      {
        "ticker": "TUREX",
        "name": "Tureks Tur.Taşımacılık",
        "agirlik": 0.0737,
        "degisim": -8.2192,
        "katki": -0.0061
      },
      {
        "ticker": "GRTHO",
        "name": "GrainTurk Tarım",
        "agirlik": 0.1433,
        "degisim": -4.4985,
        "katki": -0.0064
      },
      {
        "ticker": "TSKB",
        "name": "TSKB",
        "agirlik": 0.3209,
        "degisim": -2.269,
        "katki": -0.0073
      },
      {
        "ticker": "BRYAT",
        "name": "Borusan Yatırım",
        "agirlik": 0.1844,
        "degisim": -4.2575,
        "katki": -0.0079
      },
      {
        "ticker": "ENERY",
        "name": "Enerya Enerji",
        "agirlik": 0.4022,
        "degisim": -2.0284,
        "katki": -0.0082
      },
      {
        "ticker": "DAPGM",
        "name": "Dap Gayrimenkul",
        "agirlik": 0.2083,
        "degisim": -3.9848,
        "katki": -0.0083
      },
      {
        "ticker": "BERA",
        "name": "Bera Holding",
        "agirlik": 0.171,
        "degisim": -5.3991,
        "katki": -0.0092
      },
      {
        "ticker": "OBAMS",
        "name": "Oba Makarnacılık",
        "agirlik": 0.1105,
        "degisim": -8.37,
        "katki": -0.0092
      },
      {
        "ticker": "ENJSA",
        "name": "Enerjisa Enerji",
        "agirlik": 0.5527,
        "degisim": -1.8501,
        "katki": -0.0102
      },
      {
        "ticker": "AKSEN",
        "name": "Aksa Enerji",
        "agirlik": 0.4477,
        "degisim": -2.3754,
        "katki": -0.0106
      },
      {
        "ticker": "GLRMK",
        "name": "Gülermak Ağır Sanayi",
        "agirlik": 0.3338,
        "degisim": -3.4734,
        "katki": -0.0116
      },
      {
        "ticker": "SKBNK",
        "name": "Şekerbank",
        "agirlik": 0.4383,
        "degisim": -2.6658,
        "katki": -0.0117
      },
      {
        "ticker": "FENER",
        "name": "Fenerbahce Futbol A.Ş.",
        "agirlik": 0.1628,
        "degisim": -7.362,
        "katki": -0.012
      },
      {
        "ticker": "AKSA",
        "name": "Aksa",
        "agirlik": 0.3181,
        "degisim": -4.3796,
        "katki": -0.0139
      },
      {
        "ticker": "TRENJ",
        "name": "TR Doğal Enerji Kaynakları",
        "agirlik": 0.1695,
        "degisim": -8.6433,
        "katki": -0.0147
      },
      {
        "ticker": "TTKOM",
        "name": "Türk Telekom",
        "agirlik": 0.6553,
        "degisim": -2.2709,
        "katki": -0.0149
      },
      {
        "ticker": "KRDMD",
        "name": "Kardemir (D)",
        "agirlik": 0.6706,
        "degisim": -2.3717,
        "katki": -0.0159
      },
      {
        "ticker": "ENKAI",
        "name": "Enka İnşaat",
        "agirlik": 1.0308,
        "degisim": -1.6181,
        "katki": -0.0167
      },
      {
        "ticker": "CANTE",
        "name": "Çan2 Termik A.S",
        "agirlik": 0.2252,
        "degisim": -7.4324,
        "katki": -0.0167
      },
      {
        "ticker": "CWENE",
        "name": "Cw Enerji",
        "agirlik": 0.2405,
        "degisim": -7.4747,
        "katki": -0.018
      },
      {
        "ticker": "OYAKC",
        "name": "Oyak Çimento",
        "agirlik": 0.4566,
        "degisim": -3.9705,
        "katki": -0.0181
      },
      {
        "ticker": "DOAS",
        "name": "Doğuş Otomotiv",
        "agirlik": 0.3641,
        "degisim": -5.7276,
        "katki": -0.0209
      },
      {
        "ticker": "EFOR",
        "name": "Efor Yat. San.",
        "agirlik": 0.2539,
        "degisim": -8.2184,
        "katki": -0.0209
      },
      {
        "ticker": "ODAS",
        "name": "Odaş Elektrik Üretim",
        "agirlik": 0.2082,
        "degisim": -10.0735,
        "katki": -0.021
      },
      {
        "ticker": "CVKMD",
        "name": "Cvk Maden",
        "agirlik": 0.3824,
        "degisim": -5.6437,
        "katki": -0.0216
      },
      {
        "ticker": "ANSGR",
        "name": "Anadolu Sigorta",
        "agirlik": 0.444,
        "degisim": -4.8831,
        "katki": -0.0217
      },
      {
        "ticker": "MGROS",
        "name": "Migros",
        "agirlik": 1.4428,
        "degisim": -1.607,
        "katki": -0.0232
      },
      {
        "ticker": "BTCIM",
        "name": "Batıçim",
        "agirlik": 0.4921,
        "degisim": -4.7619,
        "katki": -0.0234
      },
      {
        "ticker": "EKGYO",
        "name": "Emlak Konut GYO",
        "agirlik": 0.8765,
        "degisim": -2.7455,
        "katki": -0.0241
      },
      {
        "ticker": "ULKER",
        "name": "Ülker Bisküvi",
        "agirlik": 0.3834,
        "degisim": -6.7766,
        "katki": -0.026
      },
      {
        "ticker": "MAVI",
        "name": "Mavi Giyim Sanayi Tic.A.S",
        "agirlik": 0.5241,
        "degisim": -5.0608,
        "katki": -0.0265
      },
      {
        "ticker": "CIMSA",
        "name": "Çimsa",
        "agirlik": 0.4765,
        "degisim": -5.5874,
        "katki": -0.0266
      },
      {
        "ticker": "BRSAN",
        "name": "Borusan Birleşik Boru Fab.",
        "agirlik": 0.3866,
        "degisim": -6.9501,
        "katki": -0.0269
      },
      {
        "ticker": "KCHOL",
        "name": "Koç Holding",
        "agirlik": 3.0118,
        "degisim": -0.9128,
        "katki": -0.0275
      },
      {
        "ticker": "PGSUS",
        "name": "Pegasus Hava Taşımacılığı",
        "agirlik": 0.95,
        "degisim": -2.9041,
        "katki": -0.0276
      },
      {
        "ticker": "RALYH",
        "name": "Ral Yatırım Holding",
        "agirlik": 0.4218,
        "degisim": -6.6452,
        "katki": -0.028
      },
      {
        "ticker": "PETKM",
        "name": "Petkim",
        "agirlik": 0.5427,
        "degisim": -5.1826,
        "katki": -0.0281
      },
      {
        "ticker": "MIATK",
        "name": "Mia Teknoloji",
        "agirlik": 0.2647,
        "degisim": -10.7679,
        "katki": -0.0285
      },
      {
        "ticker": "ECILC",
        "name": "Eczacıbaşı İlaç",
        "agirlik": 0.2621,
        "degisim": -11.1568,
        "katki": -0.0292
      },
      {
        "ticker": "TABGD",
        "name": "Tab Gıda",
        "agirlik": 0.3215,
        "degisim": -9.4106,
        "katki": -0.0303
      },
      {
        "ticker": "PSGYO",
        "name": "Pasifik GYO",
        "agirlik": 0.2268,
        "degisim": -13.4366,
        "katki": -0.0305
      },
      {
        "ticker": "MPARK",
        "name": "MLP Sağlık Hizmetleri",
        "agirlik": 0.7731,
        "degisim": -3.9823,
        "katki": -0.0308
      },
      {
        "ticker": "TAVHL",
        "name": "TAV Holding",
        "agirlik": 1.1704,
        "degisim": -2.7778,
        "katki": -0.0325
      },
      {
        "ticker": "TRMET",
        "name": "TR Anadolu Metal",
        "agirlik": 0.4086,
        "degisim": -8.0172,
        "katki": -0.0328
      },
      {
        "ticker": "TURSG",
        "name": "Türkiye Sigorta",
        "agirlik": 0.666,
        "degisim": -4.9536,
        "katki": -0.033
      },
      {
        "ticker": "SARKY",
        "name": "Sarkuysan",
        "agirlik": 0.5231,
        "degisim": -6.4698,
        "katki": -0.0338
      },
      {
        "ticker": "TUPRS",
        "name": "Tüpraş",
        "agirlik": 4.6768,
        "degisim": -0.7703,
        "katki": -0.036
      },
      {
        "ticker": "VAKBN",
        "name": "Vakıfbank",
        "agirlik": 0.551,
        "degisim": -6.548,
        "katki": -0.0361
      },
      {
        "ticker": "GESAN",
        "name": "Girişim Elektrik",
        "agirlik": 0.2749,
        "degisim": -13.8704,
        "katki": -0.0381
      },
      {
        "ticker": "KUYAS",
        "name": "Kuyas Yatırım AŞ",
        "agirlik": 0.6179,
        "degisim": -6.4763,
        "katki": -0.04
      },
      {
        "ticker": "SISE",
        "name": "Şişecam",
        "agirlik": 1.4961,
        "degisim": -2.7202,
        "katki": -0.0407
      },
      {
        "ticker": "PASEU",
        "name": "Pasifik Eurasia",
        "agirlik": 0.6325,
        "degisim": -6.6667,
        "katki": -0.0422
      },
      {
        "ticker": "HALKB",
        "name": "Halkbank",
        "agirlik": 0.6056,
        "degisim": -7.3015,
        "katki": -0.0442
      },
      {
        "ticker": "MAGEN",
        "name": "Margün Enerji",
        "agirlik": 0.27,
        "degisim": -16.5033,
        "katki": -0.0446
      },
      {
        "ticker": "TOASO",
        "name": "Tofaş Fabrika",
        "agirlik": 0.8923,
        "degisim": -5.5011,
        "katki": -0.0491
      },
      {
        "ticker": "HEKTS",
        "name": "Hektaş",
        "agirlik": 0.2888,
        "degisim": -18.0905,
        "katki": -0.0522
      },
      {
        "ticker": "FROTO",
        "name": "Ford Otosan",
        "agirlik": 1.2206,
        "degisim": -4.7301,
        "katki": -0.0577
      },
      {
        "ticker": "TCELL",
        "name": "Turkcell",
        "agirlik": 2.3792,
        "degisim": -2.7385,
        "katki": -0.0652
      },
      {
        "ticker": "EUPWR",
        "name": "Europower Enerji",
        "agirlik": 0.4492,
        "degisim": -17.3958,
        "katki": -0.0781
      },
      {
        "ticker": "GUBRF",
        "name": "Gübre Fabrikaları",
        "agirlik": 0.7703,
        "degisim": -10.9037,
        "katki": -0.084
      },
      {
        "ticker": "GARAN",
        "name": "Garanti Bankası",
        "agirlik": 1.8542,
        "degisim": -4.5929,
        "katki": -0.0852
      },
      {
        "ticker": "SAHOL",
        "name": "Sabancı Holding",
        "agirlik": 2.4297,
        "degisim": -3.9902,
        "katki": -0.0969
      },
      {
        "ticker": "TRALT",
        "name": "Türk Altın",
        "agirlik": 1.0143,
        "degisim": -11.3619,
        "katki": -0.1152
      },
      {
        "ticker": "KTLEV",
        "name": "Katılımevim",
        "agirlik": 2.044,
        "degisim": -5.8873,
        "katki": -0.1203
      },
      {
        "ticker": "SASA",
        "name": "Sasa Polyester Sanayi A.Ş.",
        "agirlik": 1.3667,
        "degisim": -10.219,
        "katki": -0.1397
      },
      {
        "ticker": "ISCTR",
        "name": "İş Bankası (C)",
        "agirlik": 2.7119,
        "degisim": -5.1881,
        "katki": -0.1407
      },
      {
        "ticker": "BIMAS",
        "name": "Bim Birleşik Mağazalar A.Ş",
        "agirlik": 7.0447,
        "degisim": -2.1768,
        "katki": -0.1533
      },
      {
        "ticker": "YKBNK",
        "name": "Yapı Kredi Bankası",
        "agirlik": 3.0128,
        "degisim": -8.7135,
        "katki": -0.2625
      },
      {
        "ticker": "ASTOR",
        "name": "Astor Enerji",
        "agirlik": 2.8133,
        "degisim": -9.9518,
        "katki": -0.28
      },
      {
        "ticker": "AKBNK",
        "name": "Akbank",
        "agirlik": 4.8691,
        "degisim": -6.2805,
        "katki": -0.3058
      },
      {
        "ticker": "ASELS",
        "name": "Aselsan",
        "agirlik": 9.6902,
        "degisim": -9.8163,
        "katki": -0.9512
      }
    ],
    "monthly": [
      {
        "ticker": "DSTKF",
        "name": "Destek Finans Faktoring",
        "agirlik": 6.6843,
        "degisim": 61.9952,
        "katki": 4.1439
      },
      {
        "ticker": "AKBNK",
        "name": "Akbank",
        "agirlik": 4.8691,
        "degisim": 20.0781,
        "katki": 0.9776
      },
      {
        "ticker": "KTLEV",
        "name": "Katılımevim",
        "agirlik": 2.044,
        "degisim": 36.9183,
        "katki": 0.7546
      },
      {
        "ticker": "YKBNK",
        "name": "Yapı Kredi Bankası",
        "agirlik": 3.0128,
        "degisim": 20.6876,
        "katki": 0.6233
      },
      {
        "ticker": "THYAO",
        "name": "Türk Hava Yolları",
        "agirlik": 5.2206,
        "degisim": 10.5307,
        "katki": 0.5498
      },
      {
        "ticker": "ISCTR",
        "name": "İş Bankası (C)",
        "agirlik": 2.7119,
        "degisim": 11.2633,
        "katki": 0.3054
      },
      {
        "ticker": "TCELL",
        "name": "Turkcell",
        "agirlik": 2.3792,
        "degisim": 9.0099,
        "katki": 0.2144
      },
      {
        "ticker": "GARAN",
        "name": "Garanti Bankası",
        "agirlik": 1.8542,
        "degisim": 11.5541,
        "katki": 0.2142
      },
      {
        "ticker": "EREGL",
        "name": "Ereğli Demir Çelik",
        "agirlik": 3.1372,
        "degisim": 6.3785,
        "katki": 0.2001
      },
      {
        "ticker": "SAHOL",
        "name": "Sabancı Holding",
        "agirlik": 2.4297,
        "degisim": 5.9239,
        "katki": 0.1439
      },
      {
        "ticker": "TAVHL",
        "name": "TAV Holding",
        "agirlik": 1.1704,
        "degisim": 11.2214,
        "katki": 0.1313
      },
      {
        "ticker": "EKGYO",
        "name": "Emlak Konut GYO",
        "agirlik": 0.8765,
        "degisim": 12.0209,
        "katki": 0.1054
      },
      {
        "ticker": "KCHOL",
        "name": "Koç Holding",
        "agirlik": 3.0118,
        "degisim": 3.3316,
        "katki": 0.1003
      },
      {
        "ticker": "AEFES",
        "name": "Anadolu Efes",
        "agirlik": 0.935,
        "degisim": 10.57,
        "katki": 0.0988
      },
      {
        "ticker": "EFOR",
        "name": "Efor Yat. San.",
        "agirlik": 0.2539,
        "degisim": 35.0397,
        "katki": 0.089
      },
      {
        "ticker": "SKBNK",
        "name": "Şekerbank",
        "agirlik": 0.4383,
        "degisim": 19.8108,
        "katki": 0.0868
      },
      {
        "ticker": "BRSAN",
        "name": "Borusan Birleşik Boru Fab.",
        "agirlik": 0.3866,
        "degisim": 16.3599,
        "katki": 0.0632
      },
      {
        "ticker": "CCOLA",
        "name": "Coca-Cola İçecek A.Ş",
        "agirlik": 1.5229,
        "degisim": 3.8726,
        "katki": 0.059
      },
      {
        "ticker": "TOASO",
        "name": "Tofaş Fabrika",
        "agirlik": 0.8923,
        "degisim": 5.9122,
        "katki": 0.0528
      },
      {
        "ticker": "TRALT",
        "name": "Türk Altın",
        "agirlik": 1.0143,
        "degisim": 4.6394,
        "katki": 0.0471
      },
      {
        "ticker": "BALSU",
        "name": "Balsu Gıda",
        "agirlik": 0.1178,
        "degisim": 36.03,
        "katki": 0.0424
      },
      {
        "ticker": "AKSA",
        "name": "Aksa",
        "agirlik": 0.3181,
        "degisim": 13.1478,
        "katki": 0.0418
      },
      {
        "ticker": "ALARK",
        "name": "Alarko Holding",
        "agirlik": 0.3428,
        "degisim": 11.7126,
        "katki": 0.0402
      },
      {
        "ticker": "PGSUS",
        "name": "Pegasus Hava Taşımacılığı",
        "agirlik": 0.95,
        "degisim": 4.174,
        "katki": 0.0397
      },
      {
        "ticker": "ENERY",
        "name": "Enerya Enerji",
        "agirlik": 0.4022,
        "degisim": 9.6481,
        "katki": 0.0388
      },
      {
        "ticker": "MGROS",
        "name": "Migros",
        "agirlik": 1.4428,
        "degisim": 2.2003,
        "katki": 0.0317
      },
      {
        "ticker": "ODAS",
        "name": "Odaş Elektrik Üretim",
        "agirlik": 0.2082,
        "degisim": 15.1882,
        "katki": 0.0316
      },
      {
        "ticker": "VAKBN",
        "name": "Vakıfbank",
        "agirlik": 0.551,
        "degisim": 5.5123,
        "katki": 0.0304
      },
      {
        "ticker": "TSKB",
        "name": "TSKB",
        "agirlik": 0.3209,
        "degisim": 8.8448,
        "katki": 0.0284
      },
      {
        "ticker": "GRTHO",
        "name": "GrainTurk Tarım",
        "agirlik": 0.1433,
        "degisim": 19.2607,
        "katki": 0.0276
      },
      {
        "ticker": "EUPWR",
        "name": "Europower Enerji",
        "agirlik": 0.4492,
        "degisim": 5.4534,
        "katki": 0.0245
      },
      {
        "ticker": "AKSEN",
        "name": "Aksa Enerji",
        "agirlik": 0.4477,
        "degisim": 5.3125,
        "katki": 0.0238
      },
      {
        "ticker": "PSGYO",
        "name": "Pasifik GYO",
        "agirlik": 0.2268,
        "degisim": 10.1218,
        "katki": 0.023
      },
      {
        "ticker": "FROTO",
        "name": "Ford Otosan",
        "agirlik": 1.2206,
        "degisim": 1.7231,
        "katki": 0.021
      },
      {
        "ticker": "HALKB",
        "name": "Halkbank",
        "agirlik": 0.6056,
        "degisim": 3.1354,
        "katki": 0.019
      },
      {
        "ticker": "DAPGM",
        "name": "Dap Gayrimenkul",
        "agirlik": 0.2083,
        "degisim": 6.5263,
        "katki": 0.0136
      },
      {
        "ticker": "TTKOM",
        "name": "Türk Telekom",
        "agirlik": 0.6553,
        "degisim": 1.8776,
        "katki": 0.0123
      },
      {
        "ticker": "KRDMD",
        "name": "Kardemir (D)",
        "agirlik": 0.6706,
        "degisim": 1.5098,
        "katki": 0.0101
      },
      {
        "ticker": "KLRHO",
        "name": "Kiler Holding",
        "agirlik": 0.311,
        "degisim": 3.056,
        "katki": 0.0095
      },
      {
        "ticker": "VESTL",
        "name": "Vestel Elektronik",
        "agirlik": 0.0939,
        "degisim": 8.6495,
        "katki": 0.0081
      },
      {
        "ticker": "GLRMK",
        "name": "Gülermak Ağır Sanayi",
        "agirlik": 0.3338,
        "degisim": 1.2934,
        "katki": 0.0043
      },
      {
        "ticker": "OTKAR",
        "name": "Otokar",
        "agirlik": 0.2724,
        "degisim": 1.5583,
        "katki": 0.0042
      },
      {
        "ticker": "ANSGR",
        "name": "Anadolu Sigorta",
        "agirlik": 0.444,
        "degisim": 0.8753,
        "katki": 0.0039
      },
      {
        "ticker": "TKFEN",
        "name": "Tekfen Holding",
        "agirlik": 0.2556,
        "degisim": 1.4205,
        "katki": 0.0036
      },
      {
        "ticker": "QUAGR",
        "name": "QUA Granite",
        "agirlik": 0.1125,
        "degisim": 1.5915,
        "katki": 0.0018
      },
      {
        "ticker": "PATEK",
        "name": "Pasifik Teknoloji",
        "agirlik": 0.146,
        "degisim": 1.1775,
        "katki": 0.0017
      },
      {
        "ticker": "TRENJ",
        "name": "TR Doğal Enerji Kaynakları",
        "agirlik": 0.1695,
        "degisim": -0.1793,
        "katki": -0.0003
      },
      {
        "ticker": "OYAKC",
        "name": "Oyak Çimento",
        "agirlik": 0.4566,
        "degisim": -0.0961,
        "katki": -0.0004
      },
      {
        "ticker": "SOKM",
        "name": "Şok Marketler",
        "agirlik": 0.265,
        "degisim": -0.5435,
        "katki": -0.0014
      },
      {
        "ticker": "ALTNY",
        "name": "Altınay Savunma",
        "agirlik": 0.1331,
        "degisim": -2.1226,
        "katki": -0.0028
      },
      {
        "ticker": "GENIL",
        "name": "Gen İlaç",
        "agirlik": 0.237,
        "degisim": -1.3889,
        "katki": -0.0033
      },
      {
        "ticker": "GSRAY",
        "name": "Galatasaray Sportif A.Ş",
        "agirlik": 0.1255,
        "degisim": -2.8571,
        "katki": -0.0036
      },
      {
        "ticker": "AGHOL",
        "name": "Anadolu Grubu Holding",
        "agirlik": 0.6696,
        "degisim": -0.5952,
        "katki": -0.004
      },
      {
        "ticker": "DOAS",
        "name": "Doğuş Otomotiv",
        "agirlik": 0.3641,
        "degisim": -1.1364,
        "katki": -0.0041
      },
      {
        "ticker": "ZOREN",
        "name": "Zorlu Enerji",
        "agirlik": 0.1211,
        "degisim": -3.5599,
        "katki": -0.0043
      },
      {
        "ticker": "BRYAT",
        "name": "Borusan Yatırım",
        "agirlik": 0.1844,
        "degisim": -2.3773,
        "katki": -0.0044
      },
      {
        "ticker": "TRMET",
        "name": "TR Anadolu Metal",
        "agirlik": 0.4086,
        "degisim": -1.1121,
        "katki": -0.0045
      },
      {
        "ticker": "ARCLK",
        "name": "Arçelik",
        "agirlik": 0.2773,
        "degisim": -1.7358,
        "katki": -0.0048
      },
      {
        "ticker": "SISE",
        "name": "Şişecam",
        "agirlik": 1.4961,
        "degisim": -0.337,
        "katki": -0.005
      },
      {
        "ticker": "PASEU",
        "name": "Pasifik Eurasia",
        "agirlik": 0.6325,
        "degisim": -0.8636,
        "katki": -0.0055
      },
      {
        "ticker": "GRSEL",
        "name": "Gürsel Taşımacılık",
        "agirlik": 0.1577,
        "degisim": -3.7125,
        "katki": -0.0059
      },
      {
        "ticker": "BIMAS",
        "name": "Bim Birleşik Mağazalar A.Ş",
        "agirlik": 7.0447,
        "degisim": -0.0855,
        "katki": -0.006
      },
      {
        "ticker": "REEDR",
        "name": "Reeder",
        "agirlik": 0.0898,
        "degisim": -7.1932,
        "katki": -0.0065
      },
      {
        "ticker": "TUKAS",
        "name": "Tukaş",
        "agirlik": 0.1332,
        "degisim": -5.3942,
        "katki": -0.0072
      },
      {
        "ticker": "BTCIM",
        "name": "Batıçim",
        "agirlik": 0.4921,
        "degisim": -1.4778,
        "katki": -0.0073
      },
      {
        "ticker": "EUREN",
        "name": "Europen Endüstri",
        "agirlik": 0.1059,
        "degisim": -7.438,
        "katki": -0.0079
      },
      {
        "ticker": "TUREX",
        "name": "Tureks Tur.Taşımacılık",
        "agirlik": 0.0737,
        "degisim": -10.9903,
        "katki": -0.0081
      },
      {
        "ticker": "BERA",
        "name": "Bera Holding",
        "agirlik": 0.171,
        "degisim": -5.2322,
        "katki": -0.0089
      },
      {
        "ticker": "BSOKE",
        "name": "Batıçim Çimento",
        "agirlik": 0.3342,
        "degisim": -3.2241,
        "katki": -0.0108
      },
      {
        "ticker": "PAHOL",
        "name": "Pasifik Holding",
        "agirlik": 0.1367,
        "degisim": -10.0592,
        "katki": -0.0138
      },
      {
        "ticker": "ISMEN",
        "name": "İş Yatırım",
        "agirlik": 0.3653,
        "degisim": -3.8866,
        "katki": -0.0142
      },
      {
        "ticker": "GESAN",
        "name": "Girişim Elektrik",
        "agirlik": 0.2749,
        "degisim": -5.8278,
        "katki": -0.016
      },
      {
        "ticker": "CWENE",
        "name": "Cw Enerji",
        "agirlik": 0.2405,
        "degisim": -7.0523,
        "katki": -0.017
      },
      {
        "ticker": "TURSG",
        "name": "Türkiye Sigorta",
        "agirlik": 0.666,
        "degisim": -2.6941,
        "katki": -0.0179
      },
      {
        "ticker": "ENJSA",
        "name": "Enerjisa Enerji",
        "agirlik": 0.5527,
        "degisim": -3.3698,
        "katki": -0.0186
      },
      {
        "ticker": "CANTE",
        "name": "Çan2 Termik A.S",
        "agirlik": 0.2252,
        "degisim": -9.8684,
        "katki": -0.0222
      },
      {
        "ticker": "OBAMS",
        "name": "Oba Makarnacılık",
        "agirlik": 0.1105,
        "degisim": -21.608,
        "katki": -0.0239
      },
      {
        "ticker": "IZENR",
        "name": "İzdemir Enerji",
        "agirlik": 0.1769,
        "degisim": -14.188,
        "katki": -0.0251
      },
      {
        "ticker": "CIMSA",
        "name": "Çimsa",
        "agirlik": 0.4765,
        "degisim": -5.5874,
        "katki": -0.0266
      },
      {
        "ticker": "MAVI",
        "name": "Mavi Giyim Sanayi Tic.A.S",
        "agirlik": 0.5241,
        "degisim": -5.3372,
        "katki": -0.028
      },
      {
        "ticker": "ULKER",
        "name": "Ülker Bisküvi",
        "agirlik": 0.3834,
        "degisim": -7.5604,
        "katki": -0.029
      },
      {
        "ticker": "MPARK",
        "name": "MLP Sağlık Hizmetleri",
        "agirlik": 0.7731,
        "degisim": -4.1943,
        "katki": -0.0324
      },
      {
        "ticker": "SARKY",
        "name": "Sarkuysan",
        "agirlik": 0.5231,
        "degisim": -7.3816,
        "katki": -0.0386
      },
      {
        "ticker": "ECILC",
        "name": "Eczacıbaşı İlaç",
        "agirlik": 0.2621,
        "degisim": -14.9044,
        "katki": -0.0391
      },
      {
        "ticker": "FENER",
        "name": "Fenerbahce Futbol A.Ş.",
        "agirlik": 0.1628,
        "degisim": -24.8756,
        "katki": -0.0405
      },
      {
        "ticker": "TABGD",
        "name": "Tab Gıda",
        "agirlik": 0.3215,
        "degisim": -13.5428,
        "katki": -0.0435
      },
      {
        "ticker": "DOHOL",
        "name": "Doğan Holding",
        "agirlik": 0.45,
        "degisim": -10.4592,
        "katki": -0.0471
      },
      {
        "ticker": "MIATK",
        "name": "Mia Teknoloji",
        "agirlik": 0.2647,
        "degisim": -19.0552,
        "katki": -0.0504
      },
      {
        "ticker": "HEKTS",
        "name": "Hektaş",
        "agirlik": 0.2888,
        "degisim": -18.5,
        "katki": -0.0534
      },
      {
        "ticker": "CVKMD",
        "name": "Cvk Maden",
        "agirlik": 0.3824,
        "degisim": -14.3522,
        "katki": -0.0549
      },
      {
        "ticker": "PETKM",
        "name": "Petkim",
        "agirlik": 0.5427,
        "degisim": -13.0769,
        "katki": -0.071
      },
      {
        "ticker": "KUYAS",
        "name": "Kuyas Yatırım AŞ",
        "agirlik": 0.6179,
        "degisim": -12.3368,
        "katki": -0.0762
      },
      {
        "ticker": "SASA",
        "name": "Sasa Polyester Sanayi A.Ş.",
        "agirlik": 1.3667,
        "degisim": -6.8182,
        "katki": -0.0932
      },
      {
        "ticker": "ENKAI",
        "name": "Enka İnşaat",
        "agirlik": 1.0308,
        "degisim": -9.2537,
        "katki": -0.0954
      },
      {
        "ticker": "RALYH",
        "name": "Ral Yatırım Holding",
        "agirlik": 0.4218,
        "degisim": -30.32,
        "katki": -0.1279
      },
      {
        "ticker": "MAGEN",
        "name": "Margün Enerji",
        "agirlik": 0.27,
        "degisim": -49.82,
        "katki": -0.1345
      },
      {
        "ticker": "GUBRF",
        "name": "Gübre Fabrikaları",
        "agirlik": 0.7703,
        "degisim": -17.5455,
        "katki": -0.1352
      },
      {
        "ticker": "ASTOR",
        "name": "Astor Enerji",
        "agirlik": 2.8133,
        "degisim": -10.3118,
        "katki": -0.2901
      },
      {
        "ticker": "TUPRS",
        "name": "Tüpraş",
        "agirlik": 4.6768,
        "degisim": -7.282,
        "katki": -0.3406
      },
      {
        "ticker": "ASELS",
        "name": "Aselsan",
        "agirlik": 9.6902,
        "degisim": -6.3774,
        "katki": -0.618
      }
    ]
  },
  "sektor_katki": {
    "daily": [
      {
        "sektor": "Finans",
        "katki": -0.2756,
        "hisse_sayisi": 21,
        "eksik": 0
      },
      {
        "sektor": "Hizmetler",
        "katki": -0.1642,
        "hisse_sayisi": 9,
        "eksik": 0
      },
      {
        "sektor": "Sanayi",
        "katki": -0.1416,
        "hisse_sayisi": 32,
        "eksik": 0
      },
      {
        "sektor": "Teknoloji",
        "katki": -0.1204,
        "hisse_sayisi": 4,
        "eksik": 0
      },
      {
        "sektor": "Havayolları ve Hizm.",
        "katki": -0.0772,
        "hisse_sayisi": 3,
        "eksik": 0
      },
      {
        "sektor": "Enerji",
        "katki": -0.0732,
        "hisse_sayisi": 15,
        "eksik": 0
      },
      {
        "sektor": "Madencilik",
        "katki": -0.0444,
        "hisse_sayisi": 3,
        "eksik": 0
      },
      {
        "sektor": "Diğer",
        "katki": 0.0167,
        "hisse_sayisi": 1,
        "eksik": 0
      },
      {
        "sektor": "Gayrimenkul",
        "katki": -0.0167,
        "hisse_sayisi": 3,
        "eksik": 0
      },
      {
        "sektor": "İletişim",
        "katki": -0.0156,
        "hisse_sayisi": 2,
        "eksik": 0
      },
      {
        "sektor": "İnşaat ve Bayındırlık",
        "katki": -0.0136,
        "hisse_sayisi": 6,
        "eksik": 0
      },
      {
        "sektor": "İletişim Cihazları",
        "katki": -0.0009,
        "hisse_sayisi": 1,
        "eksik": 0
      }
    ],
    "weekly": [
      {
        "sektor": "Teknoloji",
        "katki": -0.9665,
        "hisse_sayisi": 4,
        "eksik": 0
      },
      {
        "sektor": "Finans",
        "katki": -0.8576,
        "hisse_sayisi": 21,
        "eksik": 0
      },
      {
        "sektor": "Enerji",
        "katki": -0.6015,
        "hisse_sayisi": 15,
        "eksik": 0
      },
      {
        "sektor": "Sanayi",
        "katki": -0.5416,
        "hisse_sayisi": 32,
        "eksik": 0
      },
      {
        "sektor": "Hizmetler",
        "katki": -0.2506,
        "hisse_sayisi": 9,
        "eksik": 0
      },
      {
        "sektor": "Madencilik",
        "katki": -0.1696,
        "hisse_sayisi": 3,
        "eksik": 0
      },
      {
        "sektor": "Diğer",
        "katki": -0.1203,
        "hisse_sayisi": 1,
        "eksik": 0
      },
      {
        "sektor": "İnşaat ve Bayındırlık",
        "katki": -0.0859,
        "hisse_sayisi": 6,
        "eksik": 0
      },
      {
        "sektor": "İletişim",
        "katki": -0.0801,
        "hisse_sayisi": 2,
        "eksik": 0
      },
      {
        "sektor": "Gayrimenkul",
        "katki": -0.0629,
        "hisse_sayisi": 3,
        "eksik": 0
      },
      {
        "sektor": "Havayolları ve Hizm.",
        "katki": -0.0079,
        "hisse_sayisi": 3,
        "eksik": 0
      },
      {
        "sektor": "İletişim Cihazları",
        "katki": -0.0056,
        "hisse_sayisi": 1,
        "eksik": 0
      }
    ],
    "monthly": [
      {
        "sektor": "Finans",
        "katki": 6.6165,
        "hisse_sayisi": 21,
        "eksik": 0
      },
      {
        "sektor": "Enerji",
        "katki": -0.821,
        "hisse_sayisi": 15,
        "eksik": 0
      },
      {
        "sektor": "Diğer",
        "katki": 0.7546,
        "hisse_sayisi": 1,
        "eksik": 0
      },
      {
        "sektor": "Havayolları ve Hizm.",
        "katki": 0.7208,
        "hisse_sayisi": 3,
        "eksik": 0
      },
      {
        "sektor": "Teknoloji",
        "katki": -0.6695,
        "hisse_sayisi": 4,
        "eksik": 0
      },
      {
        "sektor": "İletişim",
        "katki": 0.2267,
        "hisse_sayisi": 2,
        "eksik": 0
      },
      {
        "sektor": "İnşaat ve Bayındırlık",
        "katki": -0.2005,
        "hisse_sayisi": 6,
        "eksik": 0
      },
      {
        "sektor": "Gayrimenkul",
        "katki": 0.142,
        "hisse_sayisi": 3,
        "eksik": 0
      },
      {
        "sektor": "Madencilik",
        "katki": -0.0123,
        "hisse_sayisi": 3,
        "eksik": 0
      },
      {
        "sektor": "Hizmetler",
        "katki": -0.0117,
        "hisse_sayisi": 9,
        "eksik": 0
      },
      {
        "sektor": "Sanayi",
        "katki": 0.0075,
        "hisse_sayisi": 32,
        "eksik": 0
      },
      {
        "sektor": "İletişim Cihazları",
        "katki": -0.0065,
        "hisse_sayisi": 1,
        "eksik": 0
      }
    ]
  }
}